spotty/__init__.py
spotty/cli.py
spotty/configuration.py
spotty/utils.py
spotty/commands/__init__.py
spotty/commands/abstract_command.py
spotty/commands/abstract_config_command.py
spotty/commands/abstract_provider_command.py
spotty/commands/aws.py
spotty/commands/download.py
spotty/commands/exec.py
spotty/commands/run.py
spotty/commands/sh.py
spotty/commands/start.py
spotty/commands/status.py
spotty/commands/stop.py
spotty/commands/sync.py
spotty/commands/writers/__init__.py
spotty/commands/writers/abstract_output_writrer.py
spotty/commands/writers/null_output_writrer.py
spotty/commands/writers/output_writrer.py
spotty/config/__init__.py
spotty/config/abstract_instance_config.py
spotty/config/abstract_instance_volume.py
spotty/config/config_utils.py
spotty/config/container_config.py
spotty/config/host_path_volume.py
spotty/config/project_config.py
spotty/config/tmp_dir_volume.py
spotty/config/validation.py
spotty/deployment/__init__.py
spotty/deployment/abstract_docker_instance_manager.py
spotty/deployment/abstract_instance_manager.py
spotty/deployment/abstract_ssh_instance_manager.py
spotty/deployment/abstract_cloud_instance/__init__.py
spotty/deployment/abstract_cloud_instance/abstract_bucket_manager.py
spotty/deployment/abstract_cloud_instance/abstract_cloud_instance_manager.py
spotty/deployment/abstract_cloud_instance/abstract_data_transfer.py
spotty/deployment/abstract_cloud_instance/abstract_instance_deployment.py
spotty/deployment/abstract_cloud_instance/file_structure.py
spotty/deployment/abstract_cloud_instance/errors/__init__.py
spotty/deployment/abstract_cloud_instance/errors/bucket_not_found.py
spotty/deployment/abstract_cloud_instance/resources/__init__.py
spotty/deployment/abstract_cloud_instance/resources/abstract_bucket.py
spotty/deployment/abstract_cloud_instance/resources/abstract_instance.py
spotty/deployment/container/__init__.py
spotty/deployment/container/abstract_container_commands.py
spotty/deployment/container/abstract_container_script.py
spotty-1.3.3.dist-info/LICENSE
spotty-1.3.3.dist-info/METADATA
spotty-1.3.3.dist-info/WHEEL
spotty-1.3.3.dist-info/top_level.txt
spotty-1.3.3.dist-info/RECORD
