Metadata-Version: 2.1
Name: spotty
Version: 1.3.3
Summary: Training deep learning models on AWS and GCP instances
Home-page: https://github.com/spotty-cloud/spotty
Author: Oleg Polosin
Author-email: apls777@gmail.com
License: MIT
Platform: UNKNOWN
Classifier: Development Status :: 5 - Production/Stable
Classifier: Intended Audience :: Science/Research
Classifier: Intended Audience :: Developers
Classifier: Intended Audience :: System Administrators
Classifier: Natural Language :: English
Classifier: License :: OSI Approved :: MIT License
Classifier: Programming Language :: Python
Classifier: Programming Language :: Python :: 3
Classifier: Programming Language :: Python :: 3.6
Classifier: Programming Language :: Python :: 3.7
Requires-Dist: boto3 (>=1.9.0)
Requires-Dist: google-api-python-client (>=1.7.8)
Requires-Dist: google-cloud-storage (>=1.15.0)
Requires-Dist: cfn-flip
Requires-Dist: schema
Requires-Dist: chevron
